assets/timing_comparator.v
// Vulnerable Timing Comparator
// Vulnerability: Early termination causes timing leak
module timing_comparator (
    input clk,
    input rst,
    input [255:0] expected_key,
    input [255:0] input_key,
    output reg match,
    output reg [8:0] timing_out
);

    reg [8:0] cycle_count;
    integer i;
    reg is_match;
    reg mismatch_found;

    always @(posedge clk) begin
        if (rst) begin
            match <= 0;
            cycle_count <= 0;
            timing_out <= 0;
        end else begin
            is_match = 1;
            cycle_count = 0;
            mismatch_found = 0;
            
            for (i = 0; i < 256; i = i + 1) begin
                if (!mismatch_found) begin
                    if (expected_key[i] != input_key[i]) begin
                        is_match = 0;
                        mismatch_found = 1;
                    end else begin
                        cycle_count = cycle_count + 1;
                    end
                end
            end
            
            match <= is_match;
            timing_out <= cycle_count;
        end
    end

endmodule

assets/testbench.v
// Testbench for timing_comparator vulnerability
module testbench;
    reg clk, rst;
    reg [255:0] expected_key;
    reg [255:0] input_key;
    wire match;
    wire [8:0] timing_out;
    
    // Instantiate the vulnerable module
    timing_comparator dut (
        .clk(clk),
        .rst(rst),
        .expected_key(expected_key),
        .input_key(input_key),
        .match(match),
        .timing_out(timing_out)
    );
    
    // Secret key (hardcoded for this task)
    initial begin
        // Secret: 256-bit key to be recovered
        expected_key = 256'hDEADBEEFCAFEBABE_0123456789ABCDEF_FEDCBA9876543210_0000000000000000;
    end
    
    // Test stimulus
    initial begin
        $dumpfile("timing.vcd");
        $dumpvars(0, testbench);
        
        clk = 0;
        rst = 1;
        input_key = 256'h0;
        
        // Reset
        #10 rst = 0;
        
        // Test 1: All zeros
        #10 input_key = 256'h0;
        #10 $display("Test 1 - timing=%d, match=%b", timing_out, match);
        
        // Test 2: First byte correct
        #10 input_key = 256'hDEADBEEF00000000_00000000_00000000_00000000;
        #10 $display("Test 2 - timing=%d, match=%b", timing_out, match);
        
        // Test 3: Exact match
        #10 input_key = 256'hDEADBEEFCAFEBABE_0123456789ABCDEF_FEDCBA9876543210_0000000000000000;
        #10 $display("Test 3 - timing=%d, match=%b", timing_out, match);
        
        $finish;
    end
    
    // Clock generation
    always #5 clk = ~clk;

endmodule

assets/timing.vcd
$date
	Mon Jun 15 10:49:16 2026
$end
$version
	Icarus Verilog
$end
$timescale
	1s
$end
$scope module testbench $end
$var wire 9 ! timing_out [8:0] $end
$var wire 1 " match $end
$var reg 1 # clk $end
$var reg 256 $ expected_key [255:0] $end
$var reg 256 % input_key [255:0] $end
$var reg 1 & rst $end
$scope module dut $end
$var wire 1 # clk $end
$var wire 256 ' expected_key [255:0] $end
$var wire 256 ( input_key [255:0] $end
$var wire 1 & rst $end
$var reg 9 ) cycle_count [8:0] $end
$var reg 1 * is_match $end
$var reg 1 " match $end
$var reg 1 + mismatch_found $end
$var reg 9 , timing_out [8:0] $end
$var integer 32 - i [31:0] $end
$upscope $end
$upscope $end
$enddefinitions $end
$comment Show the parameter values. $end
$dumpall
$end
#0
$dumpvars
bx -
bx ,
x+
x*
bx )
b0 (
b1101111010101101101111101110111111001010111111101011101010111110000000010010001101000101011001111000100110101011110011011110111111111110110111001011101010011000011101100101010000110010000100000000000000000000000000000000000000000000000000000000000000000000 '
1&
b0 %
b1101111010101101101111101110111111001010111111101011101010111110000000010010001101000101011001111000100110101011110011011110111111111110110111001011101010011000011101100101010000110010000100000000000000000000000000000000000000000000000000000000000000000000 $
0#
x"
bx !
$end
#5
b0 !
b0 ,
b0 )
0"
1#
#10
0#
0&
#15
b1000100 !
b1000100 ,
b1000100 )
b100000000 -
1+
0*
1#
#20
0#
#25
b100000000 -
1+
b1000100 )
0*
1#
#30
0#
#35
b100000000 -
1+
b1000100 )
0*
1#
#40
0#
b1101111010101101101111101110111100000000000000000000000000000000000000000000000000000000000000000000000000000000000000000000000000000000000000000000000000000000 %
b1101111010101101101111101110111100000000000000000000000000000000000000000000000000000000000000000000000000000000000000000000000000000000000000000000000000000000 (
#45
b100000000 -
1+
b1000100 )
0*
1#
#50
0#
#55
b100000000 -
1+
b1000100 )
0*
1#
#60
0#
b1101111010101101101111101110111111001010111111101011101010111110000000010010001101000101011001111000100110101011110011011110111111111110110111001011101010011000011101100101010000110010000100000000000000000000000000000000000000000000000000000000000000000000 %
b1101111010101101101111101110111111001010111111101011101010111110000000010010001101000101011001111000100110101011110011011110111111111110110111001011101010011000011101100101010000110010000100000000000000000000000000000000000000000000000000000000000000000000 (
#65
b100000000 !
b100000000 ,
1"
b100000000 -
0+
b100000000 )
1*
1#
